gen_readme/__init__.py
gen_readme/py.typed
gen_readme/conf/gen_readme.cfg
gen_readme/conf/gen_readme.logo
gen_readme/conf/gen_readme_util.cfg
gen_readme/conf/project.yaml
gen_readme/conf/template/README_AVR.template
gen_readme/conf/template/README_C.template
gen_readme/conf/template/README_CC.template
gen_readme/conf/template/README_JS.template
gen_readme/conf/template/README_PL.template
gen_readme/conf/template/README_PY.template
gen_readme/conf/template/README_RPI.template
gen_readme/conf/template/README_SH.template
gen_readme/conf/template/README_STM.template
gen_readme/conf/template/README_VALA.template
gen_readme/log/gen_readme.log
gen_readme/pro/__init__.py
gen_readme/pro/read_template.py
gen_readme/pro/write_template.py
usr/local/bin/gen_readme_run.py
gen_readme-1.1.3.dist-info/LICENSE
gen_readme-1.1.3.dist-info/METADATA
gen_readme-1.1.3.dist-info/WHEEL
gen_readme-1.1.3.dist-info/top_level.txt
gen_readme-1.1.3.dist-info/RECORD
